{
  "version": "7",
  "dialect": "postgresql",
  "entries": [
    {
      "idx": 0,
      "version": "7",
      "when": 1784111497738,
      "tag": "0000_platform_foundation",
      "breakpoints": true
    },
    {
      "idx": 1,
      "version": "7",
      "when": 1784112336603,
      "tag": "0001_tenant_ownership",
      "breakpoints": true
    },
    {
      "idx": 2,
      "version": "7",
      "when": 1784114693032,
      "tag": "0002_lean_felicia_hardy",
      "breakpoints": true
    },
    {
      "idx": 3,
      "version": "7",
      "when": 1784128392118,
      "tag": "0003_lonely_shiva",
      "breakpoints": true
    },
    {
      "idx": 4,
      "version": "7",
      "when": 1784133396275,
      "tag": "0004_redundant_magma",
      "breakpoints": true
    },
    {
      "idx": 5,
      "version": "7",
      "when": 1784137776355,
      "tag": "0005_empty_hex",
      "breakpoints": true
    },
    {
      "idx": 6,
      "version": "7",
      "when": 1784138441656,
      "tag": "0006_busy_lightspeed",
      "breakpoints": true
    },
    {
      "idx": 7,
      "version": "7",
      "when": 1784152359322,
      "tag": "0007_conscious_slapstick",
      "breakpoints": true
    },
    {
      "idx": 8,
      "version": "7",
      "when": 1784154488486,
      "tag": "0008_married_prism",
      "breakpoints": true
    },
    {
      "idx": 9,
      "version": "7",
      "when": 1784155992818,
      "tag": "0009_big_kid_colt",
      "breakpoints": true
    },
    {
      "idx": 10,
      "version": "7",
      "when": 1784156144789,
      "tag": "0010_tricky_marvex",
      "breakpoints": true
    },
    {
      "idx": 11,
      "version": "7",
      "when": 1784160818567,
      "tag": "0011_tearful_gateway",
      "breakpoints": true
    }
  ]
}